{
    "appKeys": {},
    "capabilities": [
        ""
    ],
    "companyName": "augeocacher@gmail.com",
    "longName": "PG Schedule",
    "projectType": "simplyjs",
    "resources": {
        "media": [
            {
                "file": "images/menu_icon.png",
                "menuIcon": true,
                "name": "IMAGE_MENU_ICON",
                "type": "png"
            },
            {
                "file": "images/logo_splash.png",
                "name": "IMAGE_LOGO_SPLASH",
                "type": "png"
            },
            {
                "file": "fonts/UbuntuMono-Regular.ttf",
                "name": "MONO_FONT_14",
                "type": "font"
            }
        ]
    },
    "shortName": "PG Schedule",
    "uuid": "12ac01b9-4e95-4a4c-b25d-462c2cd03d54",
    "versionCode": 1,
    "versionLabel": "1.0",
    "watchapp": {
        "watchface": false
    }
}
